README.md
setup.cfg
setup.py
vesicash_python.egg-info/PKG-INFO
vesicash_python.egg-info/SOURCES.txt
vesicash_python.egg-info/dependency_links.txt
vesicash_python.egg-info/requires.txt
vesicash_python.egg-info/top_level.txt
vesicashapi/__init__.py
vesicashapi/auth.py
vesicashapi/base.py
vesicashapi/payment.py
vesicashapi/transactions.py
vesicashapi/upload.py
vesicashapi/vesicash.py