Metadata-Version: 2.1
Name: vesicash-python
Version: 0.1.1rc1
Summary: A python library to consume Vesicash API
Home-page: https://github.com/vesicash/vesicash-python
Author: Precious Opusunju
Author-email: precious@vesicash.com
License: MIT
Keywords: vesicash python library
Platform: UNKNOWN
Classifier: Development Status :: 4 - Beta
Classifier: Intended Audience :: Developers
Classifier: License :: OSI Approved :: MIT License
Classifier: Programming Language :: Python :: 3
Classifier: Programming Language :: Python :: 3.6
Provides-Extra: test
